dstack_factory/__init__.py
dstack_factory/main.py
dstack_factory/tasks.py
dstack_factory-1.0.7.dist-info/DESCRIPTION.rst
dstack_factory-1.0.7.dist-info/METADATA
dstack_factory-1.0.7.dist-info/RECORD
dstack_factory-1.0.7.dist-info/WHEEL
dstack_factory-1.0.7.dist-info/entry_points.txt
dstack_factory-1.0.7.dist-info/metadata.json
dstack_factory-1.0.7.dist-info/top_level.txt
dstack_factory-1.0.7.dist-info/zip-safe
